karton_dashboard-1.6.0-nspkg.pth
karton/dashboard/__init__.py
karton/dashboard/__version__.py
karton/dashboard/app.py
karton/dashboard/cli.py
karton/dashboard/graph/__init__.py
karton/dashboard/graph/graph.py
karton/dashboard/static/bootstrap.css
karton/dashboard/static/favicon.ico
karton/dashboard/static/graph/graph.js
karton/dashboard/static/graph/style.css
karton/dashboard/templates/analysis.html
karton/dashboard/templates/crashed.html
karton/dashboard/templates/graph.html
karton/dashboard/templates/index.html
karton/dashboard/templates/layout.html
karton/dashboard/templates/queue.html
karton/dashboard/templates/queue_layout.html
karton/dashboard/templates/services.html
karton/dashboard/templates/task.html
karton_dashboard-1.6.0.dist-info/LICENSE
karton_dashboard-1.6.0.dist-info/METADATA
karton_dashboard-1.6.0.dist-info/WHEEL
karton_dashboard-1.6.0.dist-info/entry_points.txt
karton_dashboard-1.6.0.dist-info/namespace_packages.txt
karton_dashboard-1.6.0.dist-info/top_level.txt
karton_dashboard-1.6.0.dist-info/RECORD
