Metadata-Version: 2.1
Name: karton-dashboard
Version: 1.6.0
Summary: A small Flask application that allows for Karton task and queue introspection.
Home-page: https://github.com/CERT-Polska/karton-dashboard/
License: UNKNOWN
Platform: UNKNOWN
Classifier: Programming Language :: Python
Classifier: Operating System :: OS Independent
License-File: LICENSE
Requires-Dist: Flask (==3.0.0)
Requires-Dist: karton-core (<6.0.0,>=5.4.0)
Requires-Dist: mistune (<3.0.0)
Requires-Dist: networkx (==2.6.3)
Requires-Dist: prometheus-client (==0.11.0)
